pyheaven/__init__.py
pyheaven/args_utils.py
pyheaven/basic_utils.py
pyheaven/cache_utils.py
pyheaven/crypt_utils.py
pyheaven/file_utils.py
pyheaven/img_utils.py
pyheaven/llm_utils.py
pyheaven/misc_utils.py
pyheaven/plot_utils.py
pyheaven/project_utils.py
pyheaven/pyqt_utils.py
pyheaven/sandbox_utils.py
pyheaven/serialize_utils.py
pyheaven/torch_utils.py
pyheaven-0.1.6.3.dist-info/LICENSE
pyheaven-0.1.6.3.dist-info/METADATA
pyheaven-0.1.6.3.dist-info/WHEEL
pyheaven-0.1.6.3.dist-info/top_level.txt
pyheaven-0.1.6.3.dist-info/RECORD
