Metadata-Version: 2.1
Name: pyheaven
Version: 0.1.6.3
Summary: Python Heaven
Home-page: https://github.com/Magolor/
Author: Magolor
Author-email: magolorcz@gmail.com
Project-URL: Author, https://github.com/Magolor/
Classifier: Programming Language :: Python :: 3
Classifier: License :: OSI Approved :: MIT License
Classifier: Operating System :: OS Independent
Requires-Python: >=3.9
License-File: LICENSE
